PTestCase-1.0.2.dist-info/DESCRIPTION.rst
PTestCase-1.0.2.dist-info/METADATA
PTestCase-1.0.2.dist-info/RECORD
PTestCase-1.0.2.dist-info/WHEEL
PTestCase-1.0.2.dist-info/metadata.json
PTestCase-1.0.2.dist-info/top_level.txt
PTestCase-1.0.2.dist-info/zip-safe
ptestcase/__init__.py
ptestcase/tests.py
