Metadata-Version: 2.0
Name: PTestCase
Version: 1.0.2
Summary: Parametrized tests support for python builtin unitest framework
Home-page: https://github.com/canni/ptestcase
Author: Dariusz Górecki
Author-email: darek.krk@gmail.com
License: BSD License
Keywords: test,parametrized,unittest
Platform: any
Classifier: License :: OSI Approved :: BSD License
Classifier: Operating System :: OS Independent
Classifier: Development Status :: 5 - Production/Stable
Classifier: Intended Audience :: Developers
Classifier: Programming Language :: Python
Classifier: Programming Language :: Python :: 2
Classifier: Programming Language :: Python :: 2.6
Classifier: Programming Language :: Python :: 2.7
Classifier: Programming Language :: Python :: 3
Classifier: Programming Language :: Python :: 3.2
Classifier: Programming Language :: Python :: 3.3
Classifier: Programming Language :: Python :: 3.4
Requires-Dist: six
